generic_utils/__init__.py
generic_utils/__version__.py
generic_utils/base_utils.py
generic_utils/classtools.py
generic_utils/contextlib_ex.py
generic_utils/date.py
generic_utils/datetimetools.py
generic_utils/decorator_tools.py
generic_utils/dict_utils.py
generic_utils/file.py
generic_utils/five.py
generic_utils/hashlib_tools.py
generic_utils/html_tag_stripper.py
generic_utils/inspecttools.py
generic_utils/itertools_ex.py
generic_utils/json_utils.py
generic_utils/memoization.py
generic_utils/meta.py
generic_utils/meta.py.bak
generic_utils/numbers.py
generic_utils/ostools.py
generic_utils/parse.py
generic_utils/proxy.py
generic_utils/requests_utils.py
generic_utils/scraper_utils.py
generic_utils/statsdtools.py
generic_utils/threads.py
generic_utils/timedelta.py
generic_utils/types.py
generic_utils/types.py.bak
generic_utils/typetools.py
generic_utils/versioninfo.py
generic_utils/versioninfo.py.bak
generic_utils/cassandra_utils/__init__.py
generic_utils/cassandra_utils/cqlengine_tools/__init__.py
generic_utils/cassandra_utils/cqlengine_tools/connection.py
generic_utils/cassandra_utils/cqlengine_tools/data_type.py
generic_utils/cassandra_utils/cqlengine_tools/schema_tools.py
generic_utils/cassandra_utils/cqlengine_tools/test_utils.py
generic_utils/celery/__init__.py
generic_utils/celery/test_utils.py
generic_utils/collections/__init__.py
generic_utils/collections/exceptions.py
generic_utils/collections/pipeline.py
generic_utils/collections/sorted_collection.py
generic_utils/config/__init__.py
generic_utils/config/test_utils.py
generic_utils/debug_utils/__init__.py
generic_utils/elasticsearch/__init__.py
generic_utils/elasticsearch/test_utils.py
generic_utils/exceptions/__init__.py
generic_utils/exceptions/utils.py
generic_utils/execution_context/__init__.py
generic_utils/execution_context/exceptions.py
generic_utils/factory_boy/__init__.py
generic_utils/json_tools/__init__.py
generic_utils-0.20.0.dist-info/DESCRIPTION.rst
generic_utils-0.20.0.dist-info/METADATA
generic_utils-0.20.0.dist-info/RECORD
generic_utils-0.20.0.dist-info/WHEEL
generic_utils-0.20.0.dist-info/metadata.json
generic_utils-0.20.0.dist-info/top_level.txt
