Metadata-Version: 2.0
Name: generic-utils
Version: 0.20.0
Summary: A set of generic utility classes and helper functions for Python development.
Home-page: https://github.com/kevinseelbach/generic_utils
Author: Kevin Seelbach
Author-email: kevin.seelbach@gmail.com
License: MIT
Platform: UNKNOWN
Classifier: Development Status :: 5 - Production/Stable
Classifier: Intended Audience :: Developers
Classifier: License :: OSI Approved :: MIT License
Classifier: Operating System :: Unix
Classifier: Programming Language :: Python
Classifier: Programming Language :: Python :: 2.7
Classifier: Programming Language :: Python :: 3.4
Classifier: Programming Language :: Python :: 3.5
Classifier: Programming Language :: Python :: Implementation :: CPython
Classifier: Programming Language :: Python :: Implementation :: PyPy
Classifier: Topic :: Utilities
Requires-Dist: future
Requires-Dist: setuptools
Requires-Dist: six
Provides-Extra: cassandra
Requires-Dist: cassandra-driver; extra == 'cassandra'
Provides-Extra: celery_test
Requires-Dist: celery (>=3.1.20); extra == 'celery_test'
Requires-Dist: celery-testutils; extra == 'celery_test'
Requires-Dist: celery[threads]; extra == 'celery_test'
Requires-Dist: redis; extra == 'celery_test'
Provides-Extra: elasticsearch
Requires-Dist: elasticsearch; extra == 'elasticsearch'
Provides-Extra: html
Requires-Dist: beautifulsoup4 (>=4.3.2); extra == 'html'
Requires-Dist: lxml; extra == 'html'
Requires-Dist: requests; extra == 'html'
Provides-Extra: statsd
Requires-Dist: statsd; extra == 'statsd'
Provides-Extra: test_utils
Requires-Dist: ddt; extra == 'test_utils'
Requires-Dist: freezegun; extra == 'test_utils'
Requires-Dist: mock; extra == 'test_utils'
